steam_review_scraper/__init__.py
steam_review_scraper/scraper.py
steam_review_scraper-0.1.0.dist-info/LICENSE
steam_review_scraper-0.1.0.dist-info/METADATA
steam_review_scraper-0.1.0.dist-info/WHEEL
steam_review_scraper-0.1.0.dist-info/top_level.txt
steam_review_scraper-0.1.0.dist-info/RECORD
