Metadata-Version: 2.1
Name: steam-review-scraper
Version: 0.1.0
Summary: A package to scrape game reviews from Steam.
Home-page: https://github.com/Zhihan-Zhu/steam-review-scraper
Author: Zhihan Zhu
Author-email: garyzhu.zz@gmail.com
License: UNKNOWN
Keywords: steam,review,scrape,crawl
Platform: UNKNOWN
Classifier: Development Status :: 5 - Production/Stable
Classifier: Programming Language :: Python :: 3
Classifier: License :: OSI Approved :: MIT License
Requires-Python: >=3
Requires-Dist: beautifulsoup4
Requires-Dist: requests
Requires-Dist: pandas
